LICENSE
README.md
setup.py
pete_tpl/__init__.py
pete_tpl/c_type_conversion.py
pete_tpl/dll.py
pete_tpl/exception.py
pete_tpl/pete.py
pete_tpl/typedefs.py
pete_tpl.egg-info/PKG-INFO
pete_tpl.egg-info/SOURCES.txt
pete_tpl.egg-info/dependency_links.txt
pete_tpl.egg-info/requires.txt
pete_tpl.egg-info/top_level.txt
scripts/petetpl_postinstall.py