Metadata-Version: 2.1
Name: pete-tpl
Version: 0.5.1
Summary: A Jinja-like template engine
Home-page: https://github.com/pete-tpl
Author: Serg
Author-email: 1899416+dontpullthis@users.noreply.github.com
License: UNKNOWN
Platform: UNKNOWN
Classifier: Development Status :: 3 - Alpha
Classifier: Environment :: Other Environment
Classifier: Intended Audience :: Developers
Classifier: License :: OSI Approved :: MIT License
Classifier: Operating System :: OS Independent
Classifier: Programming Language :: Python :: 3
Requires-Python: >=3.6
License-File: LICENSE
